cgeniepy/__init__.py
cgeniepy/array.py
cgeniepy/chem.py
cgeniepy/data/EDC_CO2.tab
cgeniepy/data/GEBCO2002_bathy.nc
cgeniepy/data/__init__.py
cgeniepy/data/colormaps/BlGrYeOrReVi.txt
cgeniepy/data/colormaps/BuGd.txt
cgeniepy/data/colormaps/BuGr.txt
cgeniepy/data/colormaps/ODV.txt
cgeniepy/data/colormaps/Section.xml
cgeniepy/data/colormaps/WtBuGnYlRd.txt
cgeniepy/data/colormaps/Zissou1.txt
cgeniepy/data/colormaps/colorcet_r_bgyr.txt
cgeniepy/data/colormaps/cspace_BlRd.txt
cgeniepy/data/colormaps/kovesi_rainbow.txt
cgeniepy/data/colormaps/my_rainbow.txt
cgeniepy/data/colormaps/my_rainbow2.txt
cgeniepy/data/colormaps/parula.txt
cgeniepy/data/colormaps/r_terrain.txt
cgeniepy/data/colormaps/scientific_bam.txt
cgeniepy/data/colormaps/scientific_batlow.txt
cgeniepy/data/colormaps/scientific_cork.txt
cgeniepy/data/colormaps/scientific_imola.txt
cgeniepy/data/colormaps/scientific_vik.txt
cgeniepy/data/colormaps/tol_rainbow.txt
cgeniepy/data/colormaps/ukiyoe.txt
cgeniepy/data/colormaps/w5m4.txt
cgeniepy/data/context.txt
cgeniepy/data/mask_GIteiiaa_Atlantic.txt
cgeniepy/data/mask_GIteiiaa_AtlanticALL.txt
cgeniepy/data/mask_GIteiiaa_Indian.txt
cgeniepy/data/mask_GIteiiaa_IndianALL.txt
cgeniepy/data/mask_GIteiiaa_IndoPac.txt
cgeniepy/data/mask_GIteiiaa_IndoPacALL.txt
cgeniepy/data/mask_GIteiiaa_Pacific.txt
cgeniepy/data/mask_GIteiiaa_PacificALL.txt
cgeniepy/data/mask_GIteiiaa_PacificEQ.txt
cgeniepy/data/mask_GIteiiva_Atlantic.txt
cgeniepy/data/mask_GIteiiva_AtlanticALL.txt
cgeniepy/data/mask_GIteiiva_Pacific.txt
cgeniepy/data/mask_GIteiiva_PacificALL.txt
cgeniepy/data/mask_GIteiiva_PacificEQ.txt
cgeniepy/data/mask_p0055c_ALL.txt
cgeniepy/data/mask_p0055c_Atlantic.txt
cgeniepy/data/mask_p0055c_AtlanticN.txt
cgeniepy/data/mask_p0055c_Atlantic_MOC.txt
cgeniepy/data/mask_p0055c_Pacific.txt
cgeniepy/data/mask_p0055c_PacificN.txt
cgeniepy/data/mask_p0055c_Tanzania.txt
cgeniepy/data/mask_p0067f_ALL.txt
cgeniepy/data/mask_p0067f_Pacific.txt
cgeniepy/data/mask_worbe2_ALL.txt
cgeniepy-0.15.1.dist-info/WHEEL
cgeniepy-0.15.1.dist-info/METADATA
cgeniepy-0.15.1.dist-info/RECORD
