Metadata-Version: 2.3
Name: cgeniepy
Version: 0.15.1
Summary: A Python package to read, analyse and visualise cGENIE Earth System Model output
Author: Rui Ying
Author-email: Rui Ying <ying.rui@outlook.com>
License: GPL-3.0-only
Classifier: Programming Language :: Python :: 3
Classifier: License :: OSI Approved :: GNU General Public License v3 (GPLv3)
Classifier: Operating System :: OS Independent
Requires-Dist: xarray
Requires-Dist: numpy
Requires-Dist: pandas
Requires-Dist: matplotlib
Requires-Dist: cartopy
Requires-Dist: netcdf4
Requires-Dist: scipy
Requires-Dist: regionmask
Requires-Dist: geopandas
Requires-Dist: sphinx>=8.1.3 ; extra == 'docs'
Requires-Dist: sphinx-gallery>=0.19.0 ; extra == 'docs'
Requires-Dist: sphinx-design>=0.6.1 ; extra == 'docs'
Requires-Dist: autoapi>=2.0.1 ; extra == 'docs'
Requires-Dist: sphinx-autoapi>=3.6.0 ; extra == 'docs'
Requires-Dist: pydata-sphinx-theme>=0.16.1 ; extra == 'docs'
Requires-Dist: pangaeapy>=1.1.0 ; extra == 'extra'
Requires-Dist: gwspy ; extra == 'extra'
Requires-Python: >=3.10
Provides-Extra: docs
Provides-Extra: extra
